odoo/addons/account_type_menu/README.rst
odoo/addons/account_type_menu/__init__.py
odoo/addons/account_type_menu/__manifest__.py
odoo/addons/account_type_menu/i18n/account_type_menu.pot
odoo/addons/account_type_menu/i18n/ar.po
odoo/addons/account_type_menu/i18n/ca.po
odoo/addons/account_type_menu/i18n/ca_ES.po
odoo/addons/account_type_menu/i18n/de.po
odoo/addons/account_type_menu/i18n/es.po
odoo/addons/account_type_menu/i18n/es_ES.po
odoo/addons/account_type_menu/i18n/fr.po
odoo/addons/account_type_menu/i18n/hr.po
odoo/addons/account_type_menu/i18n/it.po
odoo/addons/account_type_menu/i18n/nl_NL.po
odoo/addons/account_type_menu/i18n/pt.po
odoo/addons/account_type_menu/i18n/tr.po
odoo/addons/account_type_menu/i18n/zh_CN.po
odoo/addons/account_type_menu/readme/CONTRIBUTORS.rst
odoo/addons/account_type_menu/readme/DESCRIPTION.rst
odoo/addons/account_type_menu/static/description/icon.png
odoo/addons/account_type_menu/static/description/index.html
odoo/addons/account_type_menu/views/account_type.xml
odoo12_addon_account_type_menu-12.0.1.0.0.99.dev17.dist-info/METADATA
odoo12_addon_account_type_menu-12.0.1.0.0.99.dev17.dist-info/WHEEL
odoo12_addon_account_type_menu-12.0.1.0.0.99.dev17.dist-info/top_level.txt
odoo12_addon_account_type_menu-12.0.1.0.0.99.dev17.dist-info/RECORD
